pysequitur/__init__.py
pysequitur/crawl.py
pysequitur/examples/examples.py
pysequitur/examples/files/plate.01001.dpx
pysequitur/examples/files/plate.01002.dpx
pysequitur/examples/files/plate.01003.dpx
pysequitur/examples/files/plate.01004.dpx
pysequitur/examples/files/plate.01005.dpx
pysequitur/examples/files/plate.01006.dpx
pysequitur/examples/files/plate.01007.dpx
pysequitur/examples/files/plate.01008.dpx
pysequitur/examples/files/plate.01009.dpx
pysequitur/examples/files/plate.01010.dpx
pysequitur/examples/files/render_001_final.exr
pysequitur/examples/files/render_002_final.exr
pysequitur/examples/files/render_003_final.exr
pysequitur/examples/files/render_004_final.exr
pysequitur/examples/files/render_005_final.exr
pysequitur/examples/files/render_006_final.exr
pysequitur/examples/files/render_007_final.exr
pysequitur/examples/files/render_008_final.exr
pysequitur/examples/files/render_009_final.exr
pysequitur/examples/files/render_010_final.exr
pysequitur/examples/files/shot-0100.exr
pysequitur/examples/files/shot-0101.exr
pysequitur/examples/files/shot-0102.exr
pysequitur/examples/files/shot-0103.exr
pysequitur/examples/files/shot-0104.exr
pysequitur/examples/files/shot-0105.exr
pysequitur/examples/files/shot-0106.exr
pysequitur/examples/files/shot-0107.exr
pysequitur/examples/files/shot-0108.exr
pysequitur/examples/files/shot-0109.exr
pysequitur/examples/files/shot-0110.exr
pysequitur/examples/utils.py
pysequitur/file_sequence.py
pysequitur/main.py
pysequitur-0.1.1.dist-info/LICENCE
pysequitur-0.1.1.dist-info/METADATA
pysequitur-0.1.1.dist-info/WHEEL
pysequitur-0.1.1.dist-info/entry_points.txt
pysequitur-0.1.1.dist-info/RECORD
