Metadata-Version: 2.3
Name: pysequitur
Version: 0.1.1
Summary: parsing and manipulation tool for file sequences
License: MIT
Keywords: vfx,file-sequence,image-sequence,file-management
Author: arcadeperfect
Author-email: alexander.harding@gmail.com
Requires-Python: >=3.12
Classifier: Development Status :: 4 - Beta
Classifier: Intended Audience :: Developers
Classifier: License :: OSI Approved :: MIT License
Classifier: Programming Language :: Python :: 3
Classifier: Programming Language :: Python :: 3.12
Classifier: Programming Language :: Python :: 3.13
Classifier: Topic :: Multimedia :: Graphics
Classifier: Topic :: Software Development :: Libraries :: Python Modules
Project-URL: Repository, https://github.com/arcadeperfect/pysequitur
